pysupercell/QE_ibrav_lib.py
pysupercell/__init__.py
pysupercell/arguments.py
pysupercell/pysupercell.py
PySupercell-0.0.1.dist-info/LICENSE.txt
PySupercell-0.0.1.dist-info/METADATA
PySupercell-0.0.1.dist-info/WHEEL
PySupercell-0.0.1.dist-info/top_level.txt
PySupercell-0.0.1.dist-info/RECORD
